kb25pkuser18/__init__.py
kb25pkuser18/addition.py
kb25pkuser18/subtraction.py
kb25pkuser18-0.1.2.dist-info/METADATA
kb25pkuser18-0.1.2.dist-info/WHEEL
kb25pkuser18-0.1.2.dist-info/RECORD
