Metadata-Version: 2.3
Name: kb25pkuser18
Version: 0.1.2
Summary: poetry+github
Author: kircheis
Author-email: kerniz@nate.com
Requires-Python: >=3.11
Classifier: Programming Language :: Python :: 3
Classifier: Programming Language :: Python :: 3.11
Classifier: Programming Language :: Python :: 3.12
Classifier: Programming Language :: Python :: 3.13
